tencentcloud/__init__.py
tencentcloud/ump/__init__.py
tencentcloud/ump/v20200918/__init__.py
tencentcloud/ump/v20200918/errorcodes.py
tencentcloud/ump/v20200918/models.py
tencentcloud/ump/v20200918/ump_client.py
tencentcloud_sdk_python_ump-3.0.1416.dist-info/METADATA
tencentcloud_sdk_python_ump-3.0.1416.dist-info/WHEEL
tencentcloud_sdk_python_ump-3.0.1416.dist-info/top_level.txt
tencentcloud_sdk_python_ump-3.0.1416.dist-info/RECORD
