Metadata-Version: 2.1
Name: tencentcloud-sdk-python-ump
Version: 3.0.1416
Summary: Tencent Cloud Ump SDK for Python
Home-page: https://github.com/TencentCloud/tencentcloud-sdk-python
Author: Tencent Cloud
Maintainer-email: tencentcloudapi@tencent.com
License: Apache License 2.0
Platform: any
Classifier: Development Status :: 5 - Production/Stable
Classifier: Intended Audience :: Developers
Classifier: License :: OSI Approved :: Apache Software License
Classifier: Programming Language :: Python
Classifier: Programming Language :: Python :: 2.7
Classifier: Programming Language :: Python :: 3
Classifier: Programming Language :: Python :: 3.6
Classifier: Programming Language :: Python :: 3.7
Requires-Dist: tencentcloud-sdk-python-common (==3.0.1416)
